re2shield/__init__.py
re2shield/core.py
tests/__init__.py
tests/test_core.py
re2shield-0.2.1.dist-info/LICENSE
re2shield-0.2.1.dist-info/METADATA
re2shield-0.2.1.dist-info/WHEEL
re2shield-0.2.1.dist-info/top_level.txt
re2shield-0.2.1.dist-info/RECORD
