Metadata-Version: 2.1
Name: re2shield
Version: 0.2.1
Summary: A Python library that provides a convenient interface for compiling and matching regular expression patterns using the re2 library.
Home-page: https://github.com/Npc-coder/re2shield
Author: mkCha
Author-email: dxsaq0@gmail.com
License: UNKNOWN
Platform: UNKNOWN
Classifier: License :: OSI Approved :: BSD License
Classifier: Programming Language :: Python
Classifier: Programming Language :: Python :: 3.8
Requires-Dist: google-re2
Requires-Dist: pickle5
